primerobotcli/__init__.py
primerobotcli/interface.py
primerobotcli/primerobot.py
primerobotcli-1.0.5.dist-info/METADATA
primerobotcli-1.0.5.dist-info/WHEEL
primerobotcli-1.0.5.dist-info/entry_points.txt
primerobotcli-1.0.5.dist-info/top_level.txt
primerobotcli-1.0.5.dist-info/RECORD
