Metadata-Version: 2.1
Name: primerobotcli
Version: 1.0.5
Summary: UNKNOWN
Home-page: UNKNOWN
License: UNKNOWN
Platform: UNKNOWN
Requires-Dist: Click
Requires-Dist: docker
Requires-Dist: boto3
Requires-Dist: PyYAML
Requires-Dist: typing-extensions
